demo/main.py
mcnptools/geometryGUI.py
mcnptools/mcnprun.py
pymcnp/__init__.py
pymcnp/functions.py
pymcnp/main.py
pymcnp/version.py
pymcnp/cli/__init__.py
pymcnp/cli/_io.py
pymcnp/cli/_state.py
pymcnp/cli/check.py
pymcnp/cli/convert.py
pymcnp/cli/plot.py
pymcnp/cli/run.py
pymcnp/cli/visualize.py
pymcnp/files/__init__.py
pymcnp/files/inp/__init__.py
pymcnp/files/inp/_block.py
pymcnp/files/inp/_card.py
pymcnp/files/inp/cell.py
pymcnp/files/inp/cells.py
pymcnp/files/inp/comment.py
pymcnp/files/inp/data.py
pymcnp/files/inp/datum.py
pymcnp/files/inp/inp.py
pymcnp/files/inp/surface.py
pymcnp/files/inp/surfaces.py
pymcnp/files/outp/__init__.py
pymcnp/files/outp/output.py
pymcnp/files/ptrac/__init__.py
pymcnp/files/ptrac/event.py
pymcnp/files/ptrac/header.py
pymcnp/files/ptrac/history.py
pymcnp/files/ptrac/ptrac.py
pymcnp/files/utils/__init__.py
pymcnp/files/utils/_cadquery.py
pymcnp/files/utils/_elements.py
pymcnp/files/utils/_parser.py
pymcnp/files/utils/errors.py
pymcnp/files/utils/types.py
pymcnp-0.2.0.dist-info/LICENSE
pymcnp-0.2.0.dist-info/METADATA
pymcnp-0.2.0.dist-info/WHEEL
pymcnp-0.2.0.dist-info/entry_points.txt
pymcnp-0.2.0.dist-info/top_level.txt
pymcnp-0.2.0.dist-info/RECORD
