Metadata-Version: 2.1
Name: pymcnp
Version: 0.2.0
Summary: Python-based MCNP tools.
Author-email: Mauricio Ayllon Unzueta <mauri.ayllon12@gmail.com>, Arun Persaud <apersaud@lbl.gov>, Devin Pease <dmpease@lbl.gov>
License: pymcnp Copyright (c) 2024, The Regents of the University of California,
Project-URL: Documentation, https://pymcnp.readthedocs.io/en/latest/
Project-URL: Homepage, https://github.com/mauricioAyllon/PyMCNP
Project-URL: Issues, https://github.com/mauricioAyllon/PyMCNP/issues
Project-URL: Changelog, https://github.com/mauricioAyllon/PyMCNP/blob/master/CHANGELOG.md
Classifier: Programming Language :: Python :: 3
Classifier: Operating System :: OS Independent
Classifier: Development Status :: 5 - Production/Stable
Classifier: License :: OSI Approved :: BSD License
Classifier: Intended Audience :: Science/Research
Classifier: Programming Language :: Python :: 3.10
Classifier: Programming Language :: Python :: 3.11
Classifier: Programming Language :: Python :: 3.12
Classifier: Programming Language :: Python :: 3.13
Classifier: Topic :: Scientific/Engineering :: Physics
Requires-Python: >=3.10
License-File: LICENSE
Requires-Dist: Sphinx
Requires-Dist: docopt
Requires-Dist: matplotlib
Requires-Dist: molmass
Requires-Dist: myst-parser
Requires-Dist: numpy
Requires-Dist: pandas
Requires-Dist: pytest
Requires-Dist: fastparquet
Requires-Dist: rich
Requires-Dist: scipy
Requires-Dist: sphinx-rtd-theme
